mariqt/__init__.py
mariqt/converters.py
mariqt/core.py
mariqt/directories.py
mariqt/equipment.py
mariqt/files.py
mariqt/geo.py
mariqt/image.py
mariqt/misc.py
mariqt/navigation.py
mariqt/provenance.py
mariqt/reports.py
mariqt/settings.py
mariqt/tests.py
mariqt/variables.py
mariqt/version.py
mariqt/resources/fair-marine-images/docs/schemas/annotation-v2.0.0.json
mariqt/resources/fair-marine-images/docs/schemas/ifdo-v2.0.1.json
mariqt/resources/fair-marine-images/docs/schemas/provenance-v0.1.0.json
mariqt/sources/__init__.py
mariqt/sources/dship.py
mariqt/sources/dship_settings.py
mariqt/sources/elements.py
mariqt/sources/ifdo.py
mariqt/sources/ifdo_reader.py
mariqt/sources/ofop.py
mariqt/sources/osis.py
mariqt/sources/svgs.py
mariqt/sources/underway.py
mariqt-1.0.1.dist-info/licenses/AUTHORS.md
mariqt-1.0.1.dist-info/licenses/LICENSE
mariqt-1.0.1.dist-info/METADATA
mariqt-1.0.1.dist-info/WHEEL
mariqt-1.0.1.dist-info/top_level.txt
mariqt-1.0.1.dist-info/RECORD
