Metadata-Version: 2.4
Name: mariqt
Version: 1.0.1
Summary: The MareHub & Marine Imaging Community Image QA/QC and curation toolbox
Author: Timm Schoening
Author-email: tschoening@geomar.de
Classifier: Programming Language :: Python :: 3
Classifier: License :: OSI Approved :: GNU General Public License v3 (GPLv3)
Classifier: Operating System :: OS Independent
License-File: LICENSE
License-File: AUTHORS.md
Requires-Dist: numpy
Requires-Dist: pymap3d
Requires-Dist: utm
Requires-Dist: pyyaml
Requires-Dist: requests
Requires-Dist: deepdiff
Requires-Dist: python-xmp-toolkit
Requires-Dist: jsonschema[format]
Requires-Dist: packaging
Dynamic: author
Dynamic: author-email
Dynamic: classifier
Dynamic: description
Dynamic: license-file
Dynamic: requires-dist
Dynamic: summary
